timejob/.DS_Store
timejob/__init__.py
timejob/example.py
timejob/timejob.py
timejob-0.0.1.dist-info/METADATA
timejob-0.0.1.dist-info/WHEEL
timejob-0.0.1.dist-info/licenses/LICENSE
timejob-0.0.1.dist-info/RECORD
