Metadata-Version: 2.1
Name: timejob
Version: 0.0.1
Summary: This package provides a decorator function `timejob` that can be used to measure the execution time of other functions in Python.
Project-URL: Homepage, https://github.com/cletrix/timejob
Project-URL: Bug Tracker, https://github.com/cletrix/timejob
Author-email: Cleyton Pedroza <cleytonpedroza@gmail.com>
License-File: LICENSE
Classifier: License :: OSI Approved :: MIT License
Classifier: Operating System :: OS Independent
Classifier: Programming Language :: Python :: 3
Requires-Python: >=3.7
